pygrading/__init__.py
pygrading/__main__.py
pygrading/configuration.py
pygrading/exception.py
pygrading/html.py
pygrading/init_project.py
pygrading/job.py
pygrading/job_base.py
pygrading/render.py
pygrading/testcase.py
pygrading/utils.py
pygrading/static/.gitignore
pygrading/static/Makefile
pygrading/static/README.md
pygrading/static/kernel/__init__.py
pygrading/static/kernel/__main__.py
pygrading/static/kernel/postwork.py
pygrading/static/kernel/prework.py
pygrading/static/kernel/run.py
pygrading/static/kernel/templates/__init__.py
pygrading/static/kernel/templates/html/base.jinja
pygrading/static/kernel/templates/html/index.html
pygrading-1.1.7.dist-info/LICENSE
pygrading-1.1.7.dist-info/METADATA
pygrading-1.1.7.dist-info/WHEEL
pygrading-1.1.7.dist-info/top_level.txt
pygrading-1.1.7.dist-info/RECORD
