Metadata-Version: 2.1
Name: pygrading
Version: 1.1.7
Summary: A Python ToolBox for CourseGrading platform.
Home-page: https://gitlab.educg.net/zhangmingyuan/PyGrading
Author: Charles Zhang
Author-email: 694556046@qq.com
License: UNKNOWN
Platform: UNKNOWN
Classifier: Programming Language :: Python :: 3
Classifier: Operating System :: OS Independent
Requires-Python: >=3.5
Requires-Dist: Jinja2 (>=2.11.2)
Requires-Dist: fire (>=0.3.1)
